<context>
    <name>ReadNearPoolPage</name>
    <message>
        <source>Read near the pool</source>
        <translation>Đọc gần hồ bơi</translation>
    </message>
    <message>
        <source>Your eReader is fully waterproof. Just try to keep your screen and hands dry while you're reading. If the screen gets wet, give it a quick wipe with a towel or cloth and continue reading.</source>
        <translation>Máy đọc sách của bạn hoàn toàn chống nước. Cố gắng giữ tay và màn hình khô khi đọc. Nếu màn hình bị ướt, chỉ cần lau bằng khăn khô rồi tiếp tục đọc.</translation>
    </message>
</context>
